lilliepy_static/__init__.py
lilliepy_static/main.py
lilliepy_static-0.1.0.dist-info/METADATA
lilliepy_static-0.1.0.dist-info/WHEEL
lilliepy_static-0.1.0.dist-info/top_level.txt
lilliepy_static-0.1.0.dist-info/RECORD
