Metadata-Version: 2.1
Name: lilliepy-static
Version: 0.1.0
Requires-Dist: flask >=3.0.3
